quilled/__init__.py
quilled/extract_subcircuit.py
quilled/piyfy.py
quilled/qprint.py
quilled/source.py
quilled-0.1.1.dist-info/licenses/LICENSE
quilled-0.1.1.dist-info/METADATA
quilled-0.1.1.dist-info/WHEEL
quilled-0.1.1.dist-info/top_level.txt
quilled-0.1.1.dist-info/RECORD
