Metadata-Version: 2.4
Name: quilled
Version: 0.1.1
Summary: Generate Quill quantum circuit diagrams from Qiskit circuits
Author: Mc-Zen
Project-URL: Homepage, https://github.com/Mc-Zen/quilled
Project-URL: Bug Tracker, https://github.com/Mc-Zen/quilled/issues
Keywords: quantum information,quantum circuits,typst
Classifier: Programming Language :: Python :: 3
Classifier: License :: OSI Approved :: MIT License
Classifier: Operating System :: OS Independent
Classifier: Topic :: Scientific/Engineering :: Physics
Classifier: Topic :: Scientific/Engineering :: Mathematics
Classifier: Intended Audience :: Science/Research
Requires-Python: >=3.8
License-File: LICENSE
Requires-Dist: qiskit>=0.45
Requires-Dist: typst>=0.13.2
Dynamic: license-file
